pymb/__init__.py
pymb-0.0.1.dist-info/METADATA
pymb-0.0.1.dist-info/WHEEL
pymb-0.0.1.dist-info/top_level.txt
pymb-0.0.1.dist-info/RECORD
