Metadata-Version: 2.4
Name: pymb
Version: 0.0.1
Summary: A Python framework for simulating Mini-Brain (Brain Organoid) intelligence and dynamics.
Home-page: https://github.com/seu-usuario/pymb
Author: Neuroquidit Research and Development
Author-email: luciano.silva@neuroqudit.io
License: MIT
Classifier: Programming Language :: Python :: 3
Classifier: Operating System :: OS Independent
Classifier: Intended Audience :: Science/Research
Classifier: Topic :: Scientific/Engineering
Requires-Python: >=3.8
Dynamic: author
Dynamic: author-email
Dynamic: classifier
Dynamic: description
Dynamic: description-content-type
Dynamic: home-page
Dynamic: license
Dynamic: requires-python
Dynamic: summary
